odoo8_addon_account_invoice_line_description-8.0.1.0.1.99.dev13-py2.7-nspkg.pth
odoo8_addon_account_invoice_line_description-8.0.1.0.1.99.dev13.dist-info/DESCRIPTION.rst
odoo8_addon_account_invoice_line_description-8.0.1.0.1.99.dev13.dist-info/METADATA
odoo8_addon_account_invoice_line_description-8.0.1.0.1.99.dev13.dist-info/RECORD
odoo8_addon_account_invoice_line_description-8.0.1.0.1.99.dev13.dist-info/WHEEL
odoo8_addon_account_invoice_line_description-8.0.1.0.1.99.dev13.dist-info/metadata.json
odoo8_addon_account_invoice_line_description-8.0.1.0.1.99.dev13.dist-info/namespace_packages.txt
odoo8_addon_account_invoice_line_description-8.0.1.0.1.99.dev13.dist-info/top_level.txt
odoo_addons/account_invoice_line_description/README.rst
odoo_addons/account_invoice_line_description/__init__.py
odoo_addons/account_invoice_line_description/__openerp__.py
odoo_addons/account_invoice_line_description/invoice.py
odoo_addons/account_invoice_line_description/res_config.py
odoo_addons/account_invoice_line_description/res_config_view.xml
odoo_addons/account_invoice_line_description/i18n/account_invoice_line_description.pot
odoo_addons/account_invoice_line_description/i18n/bs.po
odoo_addons/account_invoice_line_description/i18n/ca.po
odoo_addons/account_invoice_line_description/i18n/cs.po
odoo_addons/account_invoice_line_description/i18n/de.po
odoo_addons/account_invoice_line_description/i18n/es.po
odoo_addons/account_invoice_line_description/i18n/es_MX.po
odoo_addons/account_invoice_line_description/i18n/fr.po
odoo_addons/account_invoice_line_description/i18n/fr_CH.po
odoo_addons/account_invoice_line_description/i18n/hr.po
odoo_addons/account_invoice_line_description/i18n/hr_HR.po
odoo_addons/account_invoice_line_description/i18n/it.po
odoo_addons/account_invoice_line_description/i18n/nl_BE.po
odoo_addons/account_invoice_line_description/i18n/nl_NL.po
odoo_addons/account_invoice_line_description/i18n/pt_BR.po
odoo_addons/account_invoice_line_description/i18n/pt_PT.po
odoo_addons/account_invoice_line_description/i18n/sl.po
odoo_addons/account_invoice_line_description/i18n/tr.po
odoo_addons/account_invoice_line_description/i18n/tr_TR.po
odoo_addons/account_invoice_line_description/security/invoice_security.xml
odoo_addons/account_invoice_line_description/static/description/icon.png
